Sandra/__init__.py
Sandra/helpers.py
Sandra/performance.py
Sandra/sandra.py
Sandra/troy.py
Sandra-0.0.18.dist-info/LICENSE
Sandra-0.0.18.dist-info/METADATA
Sandra-0.0.18.dist-info/WHEEL
Sandra-0.0.18.dist-info/top_level.txt
Sandra-0.0.18.dist-info/RECORD
