Metadata-Version: 2.1
Name: Sandra
Version: 0.0.18
Summary: AES Stream Cipher with CFB and OpenPGP Modes
Home-page: https://github.com/lopgogo/Sandra
Author: George Assaad
Author-email: <lopgogo@gmail.com>
License: MIT
Keywords: python,encryption,decryption,cipher,cryptography
Classifier: Development Status :: 1 - Planning
Classifier: Intended Audience :: Developers
Classifier: Programming Language :: Python :: 3
Classifier: Operating System :: Unix
Classifier: Operating System :: MacOS :: MacOS X
Classifier: Operating System :: Microsoft :: Windows
License-File: LICENSE
Requires-Dist: pycryptodome
Requires-Dist: pandas
Requires-Dist: rsa
